{
  "appPageId" : "5d40fa06-1680-49d2-869a-900ced0a8eaa",
  "componentName" : "community_layout:sldsFlexibleLayout",
  "id" : "8f5c1606-e4cc-43c1-ba51-062d498bf248",
  "label" : "Thread Related List",
  "regions" : [ {
    "components" : [ {
      "componentAttributes" : {
        "backgroundImageConfig" : "",
        "backgroundImageOverlay" : "rgba(0,0,0,0)",
        "sectionConfig" : "{\"UUID\":\"1e68f810-6c03-4a9b-9da8-220ce566b705\",\"columns\":[{\"UUID\":\"fada624b-1e66-4e89-98a7-a8f559111ff9\",\"columnName\":\"Column 1\",\"columnKey\":\"col1\",\"columnWidth\":\"12\",\"seedComponents\":[]}]}"
      },
      "componentName" : "community_layout:section",
      "id" : "1e68f810-6c03-4a9b-9da8-220ce566b705",
      "regions" : [ {
        "id" : "fada624b-1e66-4e89-98a7-a8f559111ff9",
        "regionLabel" : "Column 1",
        "regionName" : "col1",
        "renditionMap" : { },
        "type" : "region"
      } ],
      "renderPriority" : "NEUTRAL",
      "renditionMap" : { },
      "scopedBrandingSetId" : null,
      "type" : "component"
    } ],
    "id" : "4d6d33c8-09df-45ec-891a-9d387ec47c40",
    "regionName" : "content",
    "type" : "region"
  } ],
  "themeLayoutType" : "Inner",
  "type" : "view",
  "viewType" : "relatedlist-a0P"
}